setup.py
srcdspy/__init__.py
srcdspy/query.py
srcdspy/rcon.py
srcdspy/util.py
srcdspy.egg-info/PKG-INFO
srcdspy.egg-info/SOURCES.txt
srcdspy.egg-info/dependency_links.txt
srcdspy.egg-info/top_level.txt