Metadata-Version: 1.0
Name: srcdspy
Version: 1.1
Summary: Library for SRCDS
Home-page: https://github.com/TronPaul/srcdspy
Author: Mark McGuire
Author-email: mark.b.mcg@gmail.com
License: LGPL
Platform: UNKNOWN
